CHANGES.txt
LICENSE.txt
README.txt
setup.py
src/getpaid/__init__.py
src/getpaid.payflowpro.egg-info/PKG-INFO
src/getpaid.payflowpro.egg-info/SOURCES.txt
src/getpaid.payflowpro.egg-info/dependency_links.txt
src/getpaid.payflowpro.egg-info/namespace_packages.txt
src/getpaid.payflowpro.egg-info/not-zip-safe
src/getpaid.payflowpro.egg-info/requires.txt
src/getpaid.payflowpro.egg-info/top_level.txt
src/getpaid/payflowpro/README.txt
src/getpaid/payflowpro/__init__.py
src/getpaid/payflowpro/configure.zcml
src/getpaid/payflowpro/interfaces.py
src/getpaid/payflowpro/paypal.py