Metadata-Version: 1.0
Name: getpaid.payflowpro
Version: 1.1
Summary: Get paid paypal payment processor functionality
Home-page: http://code.google.com/p/getpaid
Author: Rob LaRubbio
Author-email: rob@onenw.org
License: ZPL2.1
Platform: UNKNOWN
Classifier: Framework :: Plone
Classifier: Framework :: Zope3
Classifier: Programming Language :: Python
Classifier: Intended Audience :: Developers
Classifier: License :: OSI Approved :: Zope Public License
Classifier: Operating System :: OS Independent
Classifier: Topic :: Office/Business :: Financial
Classifier: Topic :: Software Development :: Libraries
